unblind/__init__.py
unblind/dataviz.py
unblind/etl.py
unblind/utils.py
unblind-0.0.6.dist-info/LICENSE
unblind-0.0.6.dist-info/METADATA
unblind-0.0.6.dist-info/WHEEL
unblind-0.0.6.dist-info/top_level.txt
unblind-0.0.6.dist-info/RECORD
