Metadata-Version: 2.1
Name: unblind
Version: 0.0.6
Summary: Unblind is a Python package to create data visualizations from data of the Plataforma Digital Nacional, Sistema Nacional Anticorrupción
Home-page: UNKNOWN
License: UNKNOWN
Platform: UNKNOWN
Requires-Python: >=3.8
Requires-Dist: Pillow (==9.3.0)
Requires-Dist: Pygments (==2.13.0)
Requires-Dist: SecretStorage (==3.3.3)
Requires-Dist: asttokens (==2.2.0)
Requires-Dist: autopep8 (==2.0.0)
Requires-Dist: backcall (==0.2.0)
Requires-Dist: bleach (==5.0.1)
Requires-Dist: build (==0.9.0)
Requires-Dist: certifi (==2022.9.24)
Requires-Dist: cffi (==1.15.1)
Requires-Dist: charset-normalizer (==2.1.1)
Requires-Dist: commonmark (==0.9.1)
Requires-Dist: contourpy (==1.0.6)
Requires-Dist: cryptography (==38.0.4)
Requires-Dist: cycler (==0.11.0)
Requires-Dist: debugpy (==1.6.4)
Requires-Dist: decorator (==5.1.1)
Requires-Dist: docutils (==0.19)
Requires-Dist: entrypoints (==0.4)
Requires-Dist: executing (==1.2.0)
Requires-Dist: fonttools (==4.38.0)
Requires-Dist: idna (==3.4)
Requires-Dist: importlib-metadata (==5.1.0)
Requires-Dist: ipykernel (==6.17.1)
Requires-Dist: ipython (==8.7.0)
Requires-Dist: jaraco.classes (==3.2.3)
Requires-Dist: jedi (==0.18.2)
Requires-Dist: jeepney (==0.8.0)
Requires-Dist: joblib (==1.2.0)
Requires-Dist: jupyter-client (==7.4.7)
Requires-Dist: jupyter-core (==5.1.0)
Requires-Dist: keyring (==23.11.0)
Requires-Dist: kiwisolver (==1.4.4)
Requires-Dist: matplotlib-inline (==0.1.6)
Requires-Dist: matplotlib (==3.6.2)
Requires-Dist: more-itertools (==9.0.0)
Requires-Dist: nest-asyncio (==1.5.6)
Requires-Dist: numpy (==1.23.5)
Requires-Dist: packaging (==21.3)
Requires-Dist: pandas (==1.5.2)
Requires-Dist: parso (==0.8.3)
Requires-Dist: pep517 (==0.13.0)
Requires-Dist: pexpect (==4.8.0)
Requires-Dist: pickleshare (==0.7.5)
Requires-Dist: pkginfo (==1.9.2)
Requires-Dist: platformdirs (==2.5.4)
Requires-Dist: prompt-toolkit (==3.0.33)
Requires-Dist: psutil (==5.9.4)
Requires-Dist: ptyprocess (==0.7.0)
Requires-Dist: pure-eval (==0.2.2)
Requires-Dist: pycodestyle (==2.10.0)
Requires-Dist: pycparser (==2.21)
Requires-Dist: pyparsing (==3.0.9)
Requires-Dist: python-dateutil (==2.8.2)
Requires-Dist: pytz (==2022.6)
Requires-Dist: pyzmq (==24.0.1)
Requires-Dist: readme-renderer (==37.3)
Requires-Dist: requests-toolbelt (==0.10.1)
Requires-Dist: requests (==2.28.1)
Requires-Dist: rfc3986 (==2.0.0)
Requires-Dist: rich (==12.6.0)
Requires-Dist: scikit-learn (==1.1.3)
Requires-Dist: scipy (==1.9.3)
Requires-Dist: seaborn (==0.12.1)
Requires-Dist: six (==1.16.0)
Requires-Dist: stack-data (==0.6.2)
Requires-Dist: threadpoolctl (==3.1.0)
Requires-Dist: tomli (==2.0.1)
Requires-Dist: tornado (==6.2)
Requires-Dist: traitlets (==5.6.0)
Requires-Dist: twine (==4.0.2)
Requires-Dist: typing-extensions (==4.4.0)
Requires-Dist: urllib3 (==1.26.13)
Requires-Dist: wcwidth (==0.2.5)
Requires-Dist: webencodings (==0.5.1)
Requires-Dist: wget (==3.2)
Requires-Dist: zipp (==3.11.0)
